notionx/__init__.py
notionx/api_endpoints.py
notionx/api_endpoints.pyi
notionx/client.py
notionx/client.pyi
notionx/errors.py
notionx/py.typed
notionx/utils.py
notionx/validation_tools.py
tests/__init__.py
tests/constants.py
tests/helpers.py
tests/test_api_exceptions.py
tests/test_clients.py
tests/test_example_codes.py
tests/test_util_functions.py
tests/test_validation_tools.py
NotionX-0.21.dist-info/LICENSE
NotionX-0.21.dist-info/METADATA
NotionX-0.21.dist-info/WHEEL
NotionX-0.21.dist-info/top_level.txt
NotionX-0.21.dist-info/RECORD
