Metadata-Version: 2.1
Name: NotionX
Version: 0.21
Summary: NotionX, a simple, easy-to-use Notion client, is based on the official SDK modification
Home-page: https://github.com/JezaChen/mumu-notion
Author: Jeza Chen
Author-email: jezachen@163.com
Classifier: Programming Language :: Python :: 3.7
Classifier: Programming Language :: Python :: 3.8
Classifier: Programming Language :: Python :: 3.9
Classifier: Programming Language :: Python :: 3.10
Classifier: Programming Language :: Python :: 3.11
Classifier: Programming Language :: Python :: 3.12
Classifier: Development Status :: 4 - Beta
Classifier: License :: OSI Approved :: MIT License
Requires-Python: >=3.7, <4
License-File: LICENSE
Requires-Dist: httpx >=0.23.0
